libmg/__init__.py
libmg/compiler/__init__.py
libmg/compiler/compiler.py
libmg/compiler/functions.py
libmg/compiler/layers.py
libmg/data/__init__.py
libmg/data/dataset.py
libmg/data/loaders.py
libmg/explainer/__init__.py
libmg/explainer/explainer.py
libmg/language/__init__.py
libmg/language/grammar.py
libmg/normalizer/__init__.py
libmg/normalizer/normalizer.py
libmg/tests/__init__.py
libmg/tests/run_tests.py
libmg/tests/test_compiler.py
libmg/tests/test_cuda.py
libmg/tests/test_explainer.py
libmg/tests/test_functions.py
libmg/tests/test_grammar.py
libmg/tests/test_normalizer.py
libmg/tests/test_visualizer.py
libmg/visualizer/__init__.py
libmg/visualizer/site_template/asset-manifest.json
libmg/visualizer/site_template/favicon.ico
libmg/visualizer/site_template/index.html
libmg/visualizer/site_template/manifest.json
libmg/visualizer/site_template/package.js
libmg/visualizer/site_template/robots.txt
libmg/visualizer/site_template/static/css/main.547b69a0.css
libmg/visualizer/site_template/static/css/main.547b69a0.css.map
libmg/visualizer/site_template/static/js/357.246fd674.js
libmg/visualizer/site_template/static/js/357.246fd674.js.LICENSE.txt
libmg/visualizer/site_template/static/js/357.246fd674.js.map
libmg/visualizer/site_template/static/js/787.38f16daf.chunk.js
libmg/visualizer/site_template/static/js/787.38f16daf.chunk.js.map
libmg/visualizer/site_template/static/js/main.600f3791.js
libmg/visualizer/site_template/static/js/main.600f3791.js.map
libmg/visualizer/visualizer.py
libmg-2.1.11.dist-info/METADATA
libmg-2.1.11.dist-info/WHEEL
libmg-2.1.11.dist-info/licenses/LICENSE
libmg-2.1.11.dist-info/RECORD
