Metadata-Version: 2.4
Name: libmg
Version: 2.1.11
Summary: The Python implementation of the μG language for programming graph neural networks
License: MIT
License-File: LICENSE
Author: Matteo Belenchia
Requires-Python: >=3.11
Classifier: License :: OSI Approved :: MIT License
Classifier: Programming Language :: Python :: 3
Classifier: Programming Language :: Python :: 3.11
Classifier: Programming Language :: Python :: 3.12
Classifier: Programming Language :: Python :: 3.13
Classifier: Programming Language :: Python :: 3.14
Requires-Dist: bidict
Requires-Dist: lark (>=1,<2)
Requires-Dist: numpy (>=1,<2)
Requires-Dist: pyvis (>=0.3,<0.4)
Requires-Dist: scipy (>=1,<2)
Requires-Dist: spektral (>=1.3,<1.4)
Requires-Dist: tensorflow (>=2.12)
Requires-Dist: tf-keras (>=2.16)
Project-URL: Documentation, https://quasylab.github.io/mG/
Project-URL: Repository, https://github.com/quasylab/mG
